synapsia/__init__.py
synapsia/synapsia.py
synapsia/synapsia_query.py
synapsia-1.0.3.dist-info/licenses/LICENSE
synapsia-1.0.3.dist-info/METADATA
synapsia-1.0.3.dist-info/WHEEL
synapsia-1.0.3.dist-info/entry_points.txt
synapsia-1.0.3.dist-info/top_level.txt
synapsia-1.0.3.dist-info/RECORD
