Metadata-Version: 2.4
Name: synapsia
Version: 1.0.3
Summary: A command-line tool to create and query RAG knowledge bases using LlamaIndex and Ollama.
Author-email: Luis Pereida <luis.pereida@sysadminctl.services>
License-Expression: MIT
Project-URL: Homepage, https://github.com/sysadminctl-services/synapsia
Project-URL: Repository, https://github.com/sysadminctl-services/synapsia
Project-URL: Bug Tracker, https://github.com/sysadminctl-services/synapsia/issues
Keywords: cli,rag,llm,ollama,llama-index,embeddings,vector,knowledge-base,python,ai
Classifier: Development Status :: 4 - Beta
Classifier: Intended Audience :: Developers
Classifier: Intended Audience :: System Administrators
Classifier: Topic :: Scientific/Engineering :: Artificial Intelligence
Classifier: Topic :: Utilities
Classifier: Programming Language :: Python :: 3
Classifier: Programming Language :: Python :: 3.9
Classifier: Programming Language :: Python :: 3.10
Classifier: Programming Language :: Python :: 3.11
Classifier: Operating System :: OS Independent
Requires-Python: >=3.9
License-File: LICENSE
Requires-Dist: llama-index
Requires-Dist: llama-index-embeddings-ollama
Requires-Dist: llama-index-llms-ollama
Dynamic: license-file
